aislug
