Metadata-Version: 1.0
Name: django-aislug
Version: 0.2.2
Summary: Intelligent slug computing
Home-page: https://github.com/aino/django-ainslug
Author: Mikko Hellsing
Author-email: mikko@aino.se
License: BSD
Platform: any
Classifier: Development Status :: 5 - Production/Stable
Classifier: Environment :: Web Environment
Classifier: Intended Audience :: Developers
Classifier: License :: OSI Approved :: BSD License
Classifier: Operating System :: OS Independent
Classifier: Programming Language :: Python
Classifier: Topic :: Internet :: WWW/HTTP :: Dynamic Content
Classifier: Framework :: Django
